{
  "_format": "hh-sol-cache-2",
  "files": {
    "/home/cako/Escritorio/myTFG/swarmRoboticBlockchain/orion-priv-network/contract/contracts/Lock.sol": {
      "lastModificationDate": 1677608900016,
      "contentHash": "ae66265769cc28ebdaa34881df95bc5e",
      "sourceName": "contracts/Lock.sol",
      "solcConfig": {
        "version": "0.8.17",
        "settings": {
          "optimizer": {
            "enabled": false,
            "runs": 200
          },
          "outputSelection": {
            "*": {
              "*": [
                "abi",
                "evm.bytecode",
                "evm.deployedBytecode",
                "evm.methodIdentifiers",
                "metadata"
              ],
              "": [
                "ast"
              ]
            }
          }
        }
      },
      "imports": [],
      "versionPragmas": [
        "^0.8.9"
      ],
      "artifacts": [
        "Lock"
      ]
    },
    "/home/cako/Escritorio/myTFG/swarmRoboticBlockchain/orion-priv-network/contract/contracts/RouteContract.sol": {
      "lastModificationDate": 1677609239144,
      "contentHash": "2ade1c8d914abff74d74dae6883bd074",
      "sourceName": "contracts/RouteContract.sol",
      "solcConfig": {
        "version": "0.8.17",
        "settings": {
          "optimizer": {
            "enabled": false,
            "runs": 200
          },
          "outputSelection": {
            "*": {
              "*": [
                "abi",
                "evm.bytecode",
                "evm.deployedBytecode",
                "evm.methodIdentifiers",
                "metadata"
              ],
              "": [
                "ast"
              ]
            }
          }
        }
      },
      "imports": [
        "@openzeppelin/contracts/utils/math/SafeMath.sol"
      ],
      "versionPragmas": [
        "0.8.17"
      ],
      "artifacts": [
        "RouteContract"
      ]
    },
    "/home/cako/node_modules/@openzeppelin/contracts/utils/math/SafeMath.sol": {
      "lastModificationDate": 1677609163884,
      "contentHash": "2337f0279507b5edf14a07067adf0d05",
      "sourceName": "@openzeppelin/contracts/utils/math/SafeMath.sol",
      "solcConfig": {
        "version": "0.8.17",
        "settings": {
          "optimizer": {
            "enabled": false,
            "runs": 200
          },
          "outputSelection": {
            "*": {
              "*": [
                "abi",
                "evm.bytecode",
                "evm.deployedBytecode",
                "evm.methodIdentifiers",
                "metadata"
              ],
              "": [
                "ast"
              ]
            }
          }
        }
      },
      "imports": [],
      "versionPragmas": [
        "^0.8.0"
      ],
      "artifacts": [
        "SafeMath"
      ]
    },
    "/home/cako/Escritorio/myTFG/swarmRoboticBlockchain/orion-priv-network/contract/contracts/RouteFactory.sol": {
      "lastModificationDate": 1677609017524,
      "contentHash": "756bfc376a9a0c3a01f843d4021cfceb",
      "sourceName": "contracts/RouteFactory.sol",
      "solcConfig": {
        "version": "0.8.17",
        "settings": {
          "optimizer": {
            "enabled": false,
            "runs": 200
          },
          "outputSelection": {
            "*": {
              "*": [
                "abi",
                "evm.bytecode",
                "evm.deployedBytecode",
                "evm.methodIdentifiers",
                "metadata"
              ],
              "": [
                "ast"
              ]
            }
          }
        }
      },
      "imports": [
        "./RouteContract.sol",
        "@openzeppelin/contracts/utils/math/SafeMath.sol"
      ],
      "versionPragmas": [
        "^0.8.9"
      ],
      "artifacts": [
        "RouteFactory"
      ]
    }
  }
}
